async_tg_bot/__init__.py
async_tg_bot/bot.py
async_tg_bot/context.py
async_tg_bot/errors.py
async_tg_bot/filters.py
async_tg_bot/handlers.py
async_tg_bot/loader.py
async_tg_bot/methods.py
async_tg_bot/run.py
async_tg_bot/types.py
async_tg_bot/utils.py
async_tg_bot-0.2.0.dist-info/WHEEL
async_tg_bot-0.2.0.dist-info/METADATA
async_tg_bot-0.2.0.dist-info/RECORD
