Metadata-Version: 2.1
Name: async-tg-bot
Version: 0.2.0
Summary: 
Author: levch
Author-email: levchenko.d.a1998@gmail.com
Requires-Python: >=3.10,<4.0
Classifier: Programming Language :: Python :: 3
Classifier: Programming Language :: Python :: 3.10
Requires-Dist: PyYAML (>=6.0,<7.0)
Requires-Dist: pydantic (>=1.9.0,<2.0.0)
Requires-Dist: python-dotenv (>=0.20.0,<0.21.0)
Requires-Dist: requests (>=2.27.1,<3.0.0)
